almoststatic/__init__.py
almoststatic-1.0.5.dist-info/LICENSE
almoststatic-1.0.5.dist-info/METADATA
almoststatic-1.0.5.dist-info/WHEEL
almoststatic-1.0.5.dist-info/top_level.txt
almoststatic-1.0.5.dist-info/RECORD
