Metadata-Version: 2.1
Name: almoststatic
Version: 1.0.5
Summary: Use Jinja2 template system to build static pages with Flask integration
Home-page: https://gitlab.com/claudio.driussi/almoststatic
Author: Claudio driussi
Author-email: claudio.driussi@gmail.com
License: LGPL
Keywords: Flask,static,web,"static pages","static sites",html
Platform: any
Classifier: Development Status :: 5 - Production/Stable
Classifier: Environment :: Web Environment
Classifier: Framework :: Flask
Classifier: Intended Audience :: Developers
Classifier: Intended Audience :: Other Audience
Classifier: License :: OSI Approved :: GNU Lesser General Public License v3 or later (LGPLv3+)
Classifier: Operating System :: OS Independent
Classifier: Programming Language :: Python :: 3 :: Only
Classifier: Topic :: Internet
Classifier: Topic :: Internet :: WWW/HTTP
Requires-Python: >=3.6
License-File: LICENSE
Requires-Dist: Flask
Requires-Dist: Markdown
Requires-Dist: pyyaml
